smooth_transcriber/__init__.py
smooth_transcriber/config.py
smooth_transcriber/encoder.py
smooth_transcriber/events.py
smooth_transcriber/media_format.py
smooth_transcriber/transcriber.py
smooth_transcriber-0.2.0.dist-info/METADATA
smooth_transcriber-0.2.0.dist-info/WHEEL
smooth_transcriber-0.2.0.dist-info/top_level.txt
smooth_transcriber-0.2.0.dist-info/RECORD
