Metadata-Version: 2.4
Name: smooth-transcriber
Version: 0.2.0
Summary: Async streaming speech-to-text helper built on Google Cloud Speech
Author: Trans Project
License: MIT
Project-URL: Homepage, https://example.com/smooth-transcriber
Project-URL: Repository, https://example.com/smooth-transcriber
Requires-Python: >=3.9
Requires-Dist: google-cloud-speech>=2.25.0
Requires-Dist: google-auth>=2.6.0
Requires-Dist: av>=10.0.0
Provides-Extra: dev
Requires-Dist: pytest>=8.0.0; extra == "dev"
Requires-Dist: pytest-asyncio>=1.0.0; extra == "dev"
Requires-Dist: pytest-cov>=4.0.0; extra == "dev"
